onyxcloud/Utils.py
onyxcloud/__init__.py
onyxcloud/chat.py
onyxcloud/model/model
onyxcloud/model/modelpt
onyxcloud/utils/__init__.py
onyxcloud/utils/modelupdate.py
onyxcloud/utils/plot.py
onyxcloud/utils/winprox.py
onyxcloud-1.12.9.dist-info/licenses/LICENSE
onyxcloud-1.12.9.dist-info/METADATA
onyxcloud-1.12.9.dist-info/WHEEL
onyxcloud-1.12.9.dist-info/entry_points.txt
onyxcloud-1.12.9.dist-info/top_level.txt
onyxcloud-1.12.9.dist-info/RECORD
