Metadata-Version: 2.4
Name: onyxcloud
Version: 1.12.9
Summary: Python package for the OnyxCloud CTF challenge. Part 1
Author: CTFByte
Author-email: dev@ctfbyte.com
License: MIT
Classifier: Programming Language :: Python :: 3
Classifier: License :: OSI Approved :: MIT License
Classifier: Operating System :: OS Independent
Requires-Python: >=3.10
License-File: LICENSE
Requires-Dist: torch==2.6.0
Requires-Dist: numpy==2.1.3
Requires-Dist: pypac==0.16.5
Requires-Dist: matplotlib==3.9.3
Requires-Dist: requests==2.32.3
Requires-Dist: ctfbyte-colorama==0.5.2
Requires-Dist: requests-kerberos==0.15.0
Requires-Dist: pywin32==310; sys_platform == "win32"
Dynamic: author
Dynamic: author-email
Dynamic: classifier
Dynamic: description
Dynamic: description-content-type
Dynamic: license
Dynamic: license-file
Dynamic: requires-dist
Dynamic: requires-python
Dynamic: summary
